Metadata-Version: 2.1
Name: shashipal
Version: 0.2
Summary: calculate library
Home-page: UNKNOWN
Author-email: admin@shashipal.me
License: UNKNOWN
Platform: UNKNOWN
License-File: LICENSE.TEXT
